config_patterns/__init__.py
config_patterns/_version.py
config_patterns/api.py
config_patterns/compat.py
config_patterns/exc.py
config_patterns/jsonutils.py
config_patterns/logger.py
config_patterns/paths.py
config_patterns/utils.py
config_patterns/aws/__init__.py
config_patterns/aws/api.py
config_patterns/aws/s3.py
config_patterns/aws/ssm.py
config_patterns/docs/__init__.py
config_patterns/patterns/__init__.py
config_patterns/patterns/hierarchy/__init__.py
config_patterns/patterns/hierarchy/api.py
config_patterns/patterns/hierarchy/impl.py
config_patterns/patterns/merge_key_value/__init__.py
config_patterns/patterns/merge_key_value/api.py
config_patterns/patterns/merge_key_value/impl.py
config_patterns/patterns/multi_env_json/__init__.py
config_patterns/patterns/multi_env_json/api.py
config_patterns/patterns/multi_env_json/impl.py
config_patterns/tests/__init__.py
config_patterns/tests/boto_ses.py
config_patterns/tests/helper.py
config_patterns/tests/mock.py
config_patterns/vendor/__init__.py
config_patterns/vendor/better_enum.py
config_patterns/vendor/pytest_cov_helper.py
config_patterns/vendor/strutils.py
config_patterns-1.0.7.dist-info/AUTHORS.rst
config_patterns-1.0.7.dist-info/LICENSE.txt
config_patterns-1.0.7.dist-info/METADATA
config_patterns-1.0.7.dist-info/WHEEL
config_patterns-1.0.7.dist-info/top_level.txt
config_patterns-1.0.7.dist-info/RECORD
