Metadata-Version: 2.1
Name: config_patterns
Version: 1.0.7
Summary: Brings config management best practices for production-ready application.
Home-page: https://github.com/MacHu-GWU/config_patterns-project
Download-URL: https://pypi.python.org/pypi/config_patterns/1.0.7#downloads
Author: Sanhe Hu
Author-email: husanhe@gmail.com
Maintainer: Unknown
License: MIT
Platform: Windows
Platform: MacOS
Platform: Unix
Classifier: Development Status :: 4 - Beta
Classifier: Intended Audience :: Developers
Classifier: License :: OSI Approved :: MIT License
Classifier: Natural Language :: English
Classifier: Operating System :: Microsoft :: Windows
Classifier: Operating System :: MacOS
Classifier: Operating System :: Unix
Classifier: Programming Language :: Python
Classifier: Programming Language :: Python :: 3.7
Classifier: Programming Language :: Python :: 3.8
Classifier: Programming Language :: Python :: 3.9
Classifier: Programming Language :: Python :: 3.10
Classifier: Programming Language :: Python :: 3.11
Classifier: Programming Language :: Python :: 3.12
Classifier: Programming Language :: Python :: 3 :: Only
Requires-Python: >=3.7
License-File: LICENSE.txt
License-File: AUTHORS.rst
Requires-Dist: typing-extensions
Requires-Dist: vislog <1.0.0,>=0.1.2
Requires-Dist: cached-property >=1.5.2 ; python_version < "3.8"
Provides-Extra: aws
Requires-Dist: boto3 ; extra == 'aws'
Requires-Dist: boto-session-manager <2.0.0,>=1.3.1 ; extra == 'aws'
Requires-Dist: s3pathlib <3.0.0,>=2.0.1 ; extra == 'aws'
Requires-Dist: pysecret <3.0.0,>=2.2.3 ; extra == 'aws'
Requires-Dist: aws-console-url <2.0.0,>=1.3.2 ; extra == 'aws'
Provides-Extra: dev
Requires-Dist: pathlib-mate ; extra == 'dev'
Requires-Dist: twine ; extra == 'dev'
Requires-Dist: wheel ; extra == 'dev'
Requires-Dist: build ; extra == 'dev'
Requires-Dist: boto3 ; extra == 'dev'
Requires-Dist: boto-session-manager <2.0.0,>=1.3.1 ; extra == 'dev'
Requires-Dist: pysecret <3.0.0,>=2.2.3 ; extra == 'dev'
Requires-Dist: aws-console-url <2.0.0,>=1.3.2 ; extra == 'dev'
Requires-Dist: jupyterlab ; extra == 'dev'
Provides-Extra: doc
Requires-Dist: Sphinx ==5.3.0 ; extra == 'doc'
Requires-Dist: sphinx-jinja ==2.0.2 ; extra == 'doc'
Requires-Dist: sphinx-copybutton ==0.5.1 ; extra == 'doc'
Requires-Dist: sphinx-design ==0.5.0 ; extra == 'doc'
Requires-Dist: furo ==2023.03.27 ; extra == 'doc'
Requires-Dist: nbsphinx ==0.8.12 ; extra == 'doc'
Requires-Dist: rstobj ==1.2.1 ; extra == 'doc'
Requires-Dist: pygments ==2.15.1 ; extra == 'doc'
Requires-Dist: ipython ==8.10.0 ; extra == 'doc'
Requires-Dist: docfly ==2.0.3 ; extra == 'doc'
Provides-Extra: test
Requires-Dist: pytest ; extra == 'test'
Requires-Dist: pytest-cov ; extra == 'test'
Requires-Dist: moto <5.0.0,>=4.2.14 ; extra == 'test'
